pyfiscal/__init__.py
pyfiscal/base.py
pyfiscal/constants.py
pyfiscal/generate.py
pyfiscal/helpers.py
pyfiscal/utils.py
pyfiscal/validators.py
pyfiscal-2.1.2.dist-info/LICENSE.txt
pyfiscal-2.1.2.dist-info/METADATA
pyfiscal-2.1.2.dist-info/WHEEL
pyfiscal-2.1.2.dist-info/top_level.txt
pyfiscal-2.1.2.dist-info/RECORD
