Metadata-Version: 2.1
Name: pyfiscal
Version: 2.1.2
Summary: Pyfiscal calculation of tax data.
Home-page: https://github.com/roottsantiago/pyfiscal
Author: Tomás Santiago
Author-email: thom.sgonzalez@gmail.com
License: MIT
Keywords: RFC,CURP,NSS,fiscal,tax,SAT
Platform: UNKNOWN
Classifier: Topic :: Software Development :: Build Tools
Classifier: License :: OSI Approved :: MIT License
Classifier: Programming Language :: Python
Classifier: Programming Language :: Python :: 3
Requires-Python: >=3.9
License-File: LICENSE.txt
